{
  "openapi": "3.0.4",
  "info": {
    "title": "Smart Electric API",
    "version": "v1"
  },
  "paths": {
    "/api/ElectricData/reading": {
      "post": {
        "tags": [
          "ElectricData"
        ],
        "requestBody": {
          "content": {
            "application/json-patch+json": {
              "schema": {
                "$ref": "#/components/schemas/ElectricReadingDto"
              }
            },
            "application/json": {
              "schema": {
                "$ref": "#/components/schemas/ElectricReadingDto"
              }
            },
            "text/json": {
              "schema": {
                "$ref": "#/components/schemas/ElectricReadingDto"
              }
            },
            "application/*+json": {
              "schema": {
                "$ref": "#/components/schemas/ElectricReadingDto"
              }
            }
          }
        },
        "responses": {
          "200": {
            "description": "OK"
          }
        }
      }
    },
    "/api/ElectricData/devices": {
      "get": {
        "tags": [
          "ElectricData"
        ],
        "parameters": [
          {
            "name": "PageNumber",
            "in": "query",
            "schema": {
              "type": "integer",
              "format": "int32"
            }
          },
          {
            "name": "PageSize",
            "in": "query",
            "schema": {
              "type": "integer",
              "format": "int32"
            }
          },
          {
            "name": "Status",
            "in": "query",
            "schema": {
              "type": "string"
            }
          },
          {
            "name": "Location",
            "in": "query",
            "schema": {
              "type": "string"
            }
          },
          {
            "name": "SearchTerm",
            "in": "query",
            "schema": {
              "type": "string"
            }
          },
          {
            "name": "SortBy",
            "in": "query",
            "schema": {
              "type": "string"
            }
          },
          {
            "name": "SortOrder",
            "in": "query",
            "schema": {
              "type": "string"
            }
          }
        ],
        "responses": {
          "200": {
            "description": "OK",
            "content": {
              "text/plain": {
                "schema": {
                  "$ref": "#/components/schemas/ElectricDevicePaginatedList"
                }
              },
              "application/json": {
                "schema": {
                  "$ref": "#/components/schemas/ElectricDevicePaginatedList"
                }
              },
              "text/json": {
                "schema": {
                  "$ref": "#/components/schemas/ElectricDevicePaginatedList"
                }
              }
            }
          }
        }
      }
    },
    "/api/ElectricData/stats": {
      "get": {
        "tags": [
          "ElectricData"
        ],
        "responses": {
          "200": {
            "description": "OK",
            "content": {
              "text/plain": {
                "schema": {
                  "$ref": "#/components/schemas/DeviceStatsDto"
                }
              },
              "application/json": {
                "schema": {
                  "$ref": "#/components/schemas/DeviceStatsDto"
                }
              },
              "text/json": {
                "schema": {
                  "$ref": "#/components/schemas/DeviceStatsDto"
                }
              }
            }
          }
        }
      }
    },
    "/api/ElectricData/readings/summary": {
      "get": {
        "tags": [
          "ElectricData"
        ],
        "parameters": [
          {
            "name": "period",
            "in": "query",
            "schema": {
              "type": "string",
              "default": "30d"
            }
          }
        ],
        "responses": {
          "200": {
            "description": "OK",
            "content": {
              "text/plain": {
                "schema": {
                  "type": "array",
                  "items": {
                    "$ref": "#/components/schemas/ElectricReading"
                  }
                }
              },
              "application/json": {
                "schema": {
                  "type": "array",
                  "items": {
                    "$ref": "#/components/schemas/ElectricReading"
                  }
                }
              },
              "text/json": {
                "schema": {
                  "type": "array",
                  "items": {
                    "$ref": "#/components/schemas/ElectricReading"
                  }
                }
              }
            }
          }
        }
      }
    },
    "/api/ElectricData/devices/{id}": {
      "get": {
        "tags": [
          "ElectricData"
        ],
        "parameters": [
          {
            "name": "id",
            "in": "path",
            "required": true,
            "schema": {
              "type": "string"
            }
          }
        ],
        "responses": {
          "200": {
            "description": "OK",
            "content": {
              "text/plain": {
                "schema": {
                  "$ref": "#/components/schemas/ElectricDevice"
                }
              },
              "application/json": {
                "schema": {
                  "$ref": "#/components/schemas/ElectricDevice"
                }
              },
              "text/json": {
                "schema": {
                  "$ref": "#/components/schemas/ElectricDevice"
                }
              }
            }
          }
        }
      },
      "put": {
        "tags": [
          "ElectricData"
        ],
        "parameters": [
          {
            "name": "id",
            "in": "path",
            "required": true,
            "schema": {
              "type": "string"
            }
          }
        ],
        "requestBody": {
          "content": {
            "application/json-patch+json": {
              "schema": {
                "$ref": "#/components/schemas/ElectricDevice"
              }
            },
            "application/json": {
              "schema": {
                "$ref": "#/components/schemas/ElectricDevice"
              }
            },
            "text/json": {
              "schema": {
                "$ref": "#/components/schemas/ElectricDevice"
              }
            },
            "application/*+json": {
              "schema": {
                "$ref": "#/components/schemas/ElectricDevice"
              }
            }
          }
        },
        "responses": {
          "200": {
            "description": "OK"
          }
        }
      }
    },
    "/api/ElectricData/devices/{id}/resolve-alert": {
      "post": {
        "tags": [
          "ElectricData"
        ],
        "parameters": [
          {
            "name": "id",
            "in": "path",
            "required": true,
            "schema": {
              "type": "string"
            }
          }
        ],
        "responses": {
          "200": {
            "description": "OK"
          }
        }
      }
    },
    "/api/ElectricData/devices/{id}/readings": {
      "get": {
        "tags": [
          "ElectricData"
        ],
        "parameters": [
          {
            "name": "id",
            "in": "path",
            "required": true,
            "schema": {
              "type": "string"
            }
          },
          {
            "name": "period",
            "in": "query",
            "schema": {
              "type": "string",
              "default": "30d"
            }
          }
        ],
        "responses": {
          "200": {
            "description": "OK",
            "content": {
              "text/plain": {
                "schema": {
                  "type": "array",
                  "items": {
                    "$ref": "#/components/schemas/ElectricReading"
                  }
                }
              },
              "application/json": {
                "schema": {
                  "type": "array",
                  "items": {
                    "$ref": "#/components/schemas/ElectricReading"
                  }
                }
              },
              "text/json": {
                "schema": {
                  "type": "array",
                  "items": {
                    "$ref": "#/components/schemas/ElectricReading"
                  }
                }
              }
            }
          }
        }
      }
    },
    "/api/ElectricData/devices/{id}/daily-detail": {
      "get": {
        "tags": [
          "ElectricData"
        ],
        "parameters": [
          {
            "name": "id",
            "in": "path",
            "required": true,
            "schema": {
              "type": "string"
            }
          },
          {
            "name": "date",
            "in": "query",
            "schema": {
              "type": "string",
              "format": "date-time"
            }
          }
        ],
        "responses": {
          "200": {
            "description": "OK",
            "content": {
              "text/plain": {
                "schema": {
                  "type": "array",
                  "items": {
                    "$ref": "#/components/schemas/ElectricReading"
                  }
                }
              },
              "application/json": {
                "schema": {
                  "type": "array",
                  "items": {
                    "$ref": "#/components/schemas/ElectricReading"
                  }
                }
              },
              "text/json": {
                "schema": {
                  "type": "array",
                  "items": {
                    "$ref": "#/components/schemas/ElectricReading"
                  }
                }
              }
            }
          }
        }
      }
    },
    "/api/ElectricData/devices/{id}/logs": {
      "get": {
        "tags": [
          "ElectricData"
        ],
        "parameters": [
          {
            "name": "id",
            "in": "path",
            "required": true,
            "schema": {
              "type": "string"
            }
          }
        ],
        "responses": {
          "200": {
            "description": "OK",
            "content": {
              "text/plain": {
                "schema": {
                  "type": "array",
                  "items": {
                    "$ref": "#/components/schemas/DeviceLog"
                  }
                }
              },
              "application/json": {
                "schema": {
                  "type": "array",
                  "items": {
                    "$ref": "#/components/schemas/DeviceLog"
                  }
                }
              },
              "text/json": {
                "schema": {
                  "type": "array",
                  "items": {
                    "$ref": "#/components/schemas/DeviceLog"
                  }
                }
              }
            }
          }
        }
      },
      "post": {
        "tags": [
          "ElectricData"
        ],
        "parameters": [
          {
            "name": "id",
            "in": "path",
            "required": true,
            "schema": {
              "type": "string"
            }
          }
        ],
        "requestBody": {
          "content": {
            "application/json-patch+json": {
              "schema": {
                "$ref": "#/components/schemas/DeviceLog"
              }
            },
            "application/json": {
              "schema": {
                "$ref": "#/components/schemas/DeviceLog"
              }
            },
            "text/json": {
              "schema": {
                "$ref": "#/components/schemas/DeviceLog"
              }
            },
            "application/*+json": {
              "schema": {
                "$ref": "#/components/schemas/DeviceLog"
              }
            }
          }
        },
        "responses": {
          "200": {
            "description": "OK",
            "content": {
              "text/plain": {
                "schema": {
                  "$ref": "#/components/schemas/DeviceLog"
                }
              },
              "application/json": {
                "schema": {
                  "$ref": "#/components/schemas/DeviceLog"
                }
              },
              "text/json": {
                "schema": {
                  "$ref": "#/components/schemas/DeviceLog"
                }
              }
            }
          }
        }
      }
    },
    "/api/ElectricData/reports": {
      "post": {
        "tags": [
          "ElectricData"
        ],
        "requestBody": {
          "content": {
            "application/json-patch+json": {
              "schema": {
                "$ref": "#/components/schemas/ReportQueryParameters"
              }
            },
            "application/json": {
              "schema": {
                "$ref": "#/components/schemas/ReportQueryParameters"
              }
            },
            "text/json": {
              "schema": {
                "$ref": "#/components/schemas/ReportQueryParameters"
              }
            },
            "application/*+json": {
              "schema": {
                "$ref": "#/components/schemas/ReportQueryParameters"
              }
            }
          }
        },
        "responses": {
          "200": {
            "description": "OK",
            "content": {
              "text/plain": {
                "schema": {
                  "type": "array",
                  "items": {
                    "$ref": "#/components/schemas/ConsumptionReportItem"
                  }
                }
              },
              "application/json": {
                "schema": {
                  "type": "array",
                  "items": {
                    "$ref": "#/components/schemas/ConsumptionReportItem"
                  }
                }
              },
              "text/json": {
                "schema": {
                  "type": "array",
                  "items": {
                    "$ref": "#/components/schemas/ConsumptionReportItem"
                  }
                }
              }
            }
          }
        }
      }
    }
  },
  "components": {
    "schemas": {
      "ConsumptionReportItem": {
        "required": [
          "deviceId",
          "deviceName"
        ],
        "type": "object",
        "properties": {
          "deviceId": {
            "type": "string",
            "nullable": true
          },
          "deviceName": {
            "type": "string",
            "nullable": true
          },
          "location": {
            "type": "string",
            "nullable": true
          },
          "totalConsumption": {
            "type": "integer",
            "format": "int64"
          },
          "dailyConsumption": {
            "type": "array",
            "items": {
              "$ref": "#/components/schemas/DailyConsumption"
            },
            "nullable": true
          }
        },
        "additionalProperties": false
      },
      "DailyConsumption": {
        "type": "object",
        "properties": {
          "date": {
            "type": "string",
            "format": "date-time"
          },
          "consumption": {
            "type": "integer",
            "format": "int64"
          }
        },
        "additionalProperties": false
      },
      "DeviceLog": {
        "required": [
          "author",
          "comment",
          "deviceId",
          "newStatus"
        ],
        "type": "object",
        "properties": {
          "logId": {
            "type": "integer",
            "format": "int32"
          },
          "deviceId": {
            "minLength": 1,
            "type": "string"
          },
          "timestamp": {
            "type": "string",
            "format": "date-time"
          },
          "author": {
            "minLength": 1,
            "type": "string"
          },
          "comment": {
            "minLength": 1,
            "type": "string"
          },
          "newStatus": {
            "minLength": 1,
            "type": "string"
          },
          "device": {
            "$ref": "#/components/schemas/ElectricDevice"
          }
        },
        "additionalProperties": false
      },
      "DeviceStatsDto": {
        "type": "object",
        "properties": {
          "totalCount": {
            "type": "integer",
            "format": "int32"
          },
          "activeCount": {
            "type": "integer",
            "format": "int32"
          },
          "maintenanceCount": {
            "type": "integer",
            "format": "int32"
          },
          "alertCount": {
            "type": "integer",
            "format": "int32"
          },
          "otherCount": {
            "type": "integer",
            "format": "int32"
          }
        },
        "additionalProperties": false
      },
      "ElectricDevice": {
        "required": [
          "name"
        ],
        "type": "object",
        "properties": {
          "deviceId": {
            "type": "string",
            "nullable": true
          },
          "name": {
            "minLength": 1,
            "type": "string"
          },
          "location": {
            "type": "string",
            "nullable": true
          },
          "status": {
            "type": "string",
            "nullable": true
          },
          "networkSignal": {
            "type": "integer",
            "format": "int32",
            "nullable": true
          },
          "lastKnownVolume": {
            "type": "integer",
            "format": "int64",
            "nullable": true
          },
          "lastReadingTimestamp": {
            "type": "string",
            "format": "date-time",
            "nullable": true
          },
          "installationDate": {
            "type": "string",
            "format": "date-time",
            "nullable": true
          },
          "readings": {
            "type": "array",
            "items": {
              "$ref": "#/components/schemas/ElectricReading"
            },
            "nullable": true
          }
        },
        "additionalProperties": false
      },
      "ElectricDevicePaginatedList": {
        "type": "object",
        "properties": {
          "items": {
            "type": "array",
            "items": {
              "$ref": "#/components/schemas/ElectricDevice"
            },
            "nullable": true
          },
          "pageNumber": {
            "type": "integer",
            "format": "int32"
          },
          "totalPages": {
            "type": "integer",
            "format": "int32",
            "readOnly": true
          },
          "totalCount": {
            "type": "integer",
            "format": "int32",
            "readOnly": true
          }
        },
        "additionalProperties": false
      },
      "ElectricReading": {
        "required": [
          "consumptionSinceLast",
          "deviceId",
          "networkSignal",
          "timestamp",
          "volume"
        ],
        "type": "object",
        "properties": {
          "readingId": {
            "type": "integer",
            "format": "int64"
          },
          "deviceId": {
            "minLength": 1,
            "type": "string"
          },
          "timestamp": {
            "type": "string",
            "format": "date-time"
          },
          "volume": {
            "type": "integer",
            "format": "int64"
          },
          "consumptionSinceLast": {
            "type": "integer",
            "format": "int32"
          },
          "networkSignal": {
            "type": "integer",
            "format": "int32"
          },
          "device": {
            "$ref": "#/components/schemas/ElectricDevice"
          }
        },
        "additionalProperties": false
      },
      "ElectricReadingDto": {
        "type": "object",
        "properties": {
          "rawData": {
            "type": "string",
            "nullable": true
          }
        },
        "additionalProperties": false
      },
      "ReportQueryParameters": {
        "type": "object",
        "properties": {
          "fromDate": {
            "type": "string",
            "format": "date-time"
          },
          "toDate": {
            "type": "string",
            "format": "date-time"
          },
          "location": {
            "type": "string",
            "nullable": true
          }
        },
        "additionalProperties": false
      }
    },
    "securitySchemes": {
      "Bearer": {
        "type": "apiKey",
        "description": "Please enter JWT with Bearer into field",
        "name": "Authorization",
        "in": "header"
      }
    }
  },
  "security": [
    {
      "Bearer": [ ]
    }
  ]
}